game_assets/__init__.py
game_assets/images/__init__.py
game_assets/images/alien_bullets/__init__.py
game_assets/images/alien_bullets/alien_bullet1.png
game_assets/images/alien_bullets/alien_bullet2.png
game_assets/images/alien_bullets/alien_bullet3.png
game_assets/images/alien_bullets/alien_bullet4.png
game_assets/images/alien_bullets/alien_bullet5.png
game_assets/images/alien_bullets/alien_bullet6.png
game_assets/images/alien_bullets/alien_bullet7.png
game_assets/images/alien_bullets/arcturus_bullet.png
game_assets/images/alien_bullets/astaroth_bullet.png
game_assets/images/alien_bullets/krynnax_bullet.png
game_assets/images/alien_bullets/mothership_bullet.png
game_assets/images/alien_bullets/nebulon_bullet.png
game_assets/images/alien_bullets/nephilim_bullet.png
game_assets/images/alien_bullets/scorpion_bullet.png
game_assets/images/alien_bullets/typhon_bullet.png
game_assets/images/alien_bullets/valtor_bullet.png
game_assets/images/alien_bullets/xalaxar_bullet.png
game_assets/images/alien_bullets/xanathar_bullet.png
game_assets/images/alien_bullets/xixo_bullet.png
game_assets/images/alien_bullets/xydonix_bullet.png
game_assets/images/alien_bullets/xyranth_bullet.png
game_assets/images/alien_bullets/zorgoth_bullet.png
game_assets/images/alien_immune/__init__.py
game_assets/images/alien_immune/immune-01.png
game_assets/images/alien_immune/immune-010.png
game_assets/images/alien_immune/immune-011.png
game_assets/images/alien_immune/immune-012.png
game_assets/images/alien_immune/immune-013.png
game_assets/images/alien_immune/immune-014.png
game_assets/images/alien_immune/immune-015.png
game_assets/images/alien_immune/immune-016.png
game_assets/images/alien_immune/immune-017.png
game_assets/images/alien_immune/immune-018.png
game_assets/images/alien_immune/immune-019.png
game_assets/images/alien_immune/immune-02.png
game_assets/images/alien_immune/immune-020.png
game_assets/images/alien_immune/immune-03.png
game_assets/images/alien_immune/immune-04.png
alien_onslaught-3.3.2.dist-info/LICENSE
alien_onslaught-3.3.2.dist-info/METADATA
alien_onslaught-3.3.2.dist-info/WHEEL
alien_onslaught-3.3.2.dist-info/top_level.txt
alien_onslaught-3.3.2.dist-info/RECORD
