Metadata-Version: 2.1
Name: alien-onslaught
Version: 3.3.2
Summary: Alien Onslaught: An action-packed arcade space shooter game.
Author: Miron Alexandru
Author-email: khadaake@gmail.com
Project-URL: Source Code, https://github.com/KhadaAke/Alien-Onslaught
Classifier: Development Status :: 5 - Production/Stable
Classifier: Intended Audience :: Developers
Classifier: Intended Audience :: End Users/Desktop
Classifier: License :: OSI Approved :: MIT License
Classifier: Programming Language :: Python :: 3.11
Classifier: Operating System :: OS Independent
Classifier: Topic :: Games/Entertainment
Classifier: Topic :: Software Development :: Libraries :: pygame
License-File: LICENSE
Requires-Dist: pygame
